setup.py
ipteller/__init__.py
ipteller/address.py
ipteller/ipteller.py
ipteller/jsonip.py
ipteller/mailer.py
ipteller.egg-info/PKG-INFO
ipteller.egg-info/SOURCES.txt
ipteller.egg-info/dependency_links.txt
ipteller.egg-info/not-zip-safe
ipteller.egg-info/top_level.txt