Metadata-Version: 1.0
Name: ipteller
Version: 1.0.0
Summary: Sends an email when your IP address changes
Home-page: http://github.com/Saphyel/ipteller
Author: Saphyel
Author-email: Saphyel@gmail.com
License: MIT
Platform: UNKNOWN
